{"metadata": {"synopsis": "A Moscow-based U.S. journalist (Hal Holbrook) falls in love with a ballerina (Goldie Hawn) being followed by the police.", "rating": "20", "genre": "Classics/Comedy/Drama/Romance", "runtime": "1h 43m", "director": "Robert Ellis Miller", "studio": "UniversalPictures", "theater_date": "", "dvd_date": "Sep 11, 2015", "box_office": ""}, "reviews": {"reviews": ["Films need something beyond ensemble performances."], "rating": [""], "fresh": ["rotten"], "critic": ["Dick Lochte"], "publisher": ["data-qa=\"review-critic-publication\">Los Angeles Free Press"], "date": ["December 12, 2019"]}}