{"metadata": {"synopsis": "A British factory foreman shocks his workers with the news that his pet budgie can predict winners at the racetrack.", "rating": "72", "genre": "Comedy/Television", "runtime": "1h 30m", "director": "Gerald Thomas", "studio": "TheRankOrganisation,PeterRogersProductions", "theater_date": "", "dvd_date": "May 22, 2017", "box_office": ""}, "reviews": {"reviews": [""], "rating": ["2/5"], "fresh": ["rotten"], "critic": ["Emanuel Levy"], "publisher": ["data-qa=\"review-critic-publication\">EmanuelLevy.Com"], "date": ["August 12, 2005"]}}