{"metadata": {"synopsis": "Showman P.T. Barnum (Burl Ives) plans with a balloonist (Troy Donahue) and an inventor (Gert Frobe) to send Gen. Tom Thumb in a rocket to the moon.", "rating": "7", "genre": "Action & Adventure/Classics/Comedy/Science Fiction & Fantasy", "runtime": "1h 35m", "director": "Don Sharp", "studio": "AmericanInternat&#39;lPics", "theater_date": "", "dvd_date": "Jan 2, 2020", "box_office": ""}, "reviews": {"reviews": ["", ""], "rating": ["2/5", "1/5"], "fresh": ["rotten", "rotten"], "critic": ["Emanuel Levy", "Mark R. Leeper"], "publisher": ["data-qa=\"review-critic-publication\">EmanuelLevy.Com", "data-qa=\"review-critic-publication\">rec.arts.movies.reviews"], "date": ["November 4, 2005", "December 5, 2004"]}}