{"metadata": {"synopsis": "A police detective's (Cotter Smith) mind is linked with a boy's (Scott Curtis), which is linked with a killer demon.", "rating": "18", "genre": "Horror", "runtime": "1h 27m", "director": "Armand Mastroianni", "studio": "", "theater_date": "", "dvd_date": "May 14, 2014", "box_office": "$10.8K"}, "reviews": {"reviews": ["", "Typical, dated 80s claptrap.", ""], "rating": ["3/5", "1/5", "1/5"], "fresh": ["fresh", "rotten", "rotten"], "critic": ["Emanuel Levy", "Staci Layne Wilson", "Frank Swietek"], "publisher": ["data-qa=\"review-critic-publication\">EmanuelLevy.Com", "data-qa=\"review-critic-publication\">Fantastica Daily", "data-qa=\"review-critic-publication\">One Guy&#39;s Opinion"], "date": ["October 6, 2005", "January 27, 2005", "May 6, 2004"]}}