{"metadata": {"synopsis": "As the civil rights movement gains momentum throughout the South, Alabama sorority sister Maggie DeLoach (Ally Sheedy) is popular, attractive and engaged to Boots Claibourne (Don Michael Paul), whose father owns one of the area's largest plantations. But Maggie feels there's more to life than marrying a rich husband -- a fact her best friend, Delia (Virginia Madsen), doesn't grasp. When Maggie meets charming, socially concerned photographer Hoyt Cunningham (Treat Williams), everything changes.", "rating": "24", "genre": "Drama", "runtime": "1h 35m", "director": "Martin Davidson", "studio": "", "theater_date": "", "dvd_date": "Jan 1, 2020", "box_office": "$691.7K"}, "reviews": {"reviews": [""], "rating": ["2/5"], "fresh": ["rotten"], "critic": ["Emanuel Levy"], "publisher": ["data-qa=\"review-critic-publication\">EmanuelLevy.Com"], "date": ["August 1, 2005"]}}