{"metadata": {"synopsis": "An enthusiastic Siberian rock 'n' roll band, The Leningrad Cowboys, journeys to New York with their manager (Matti Pellonp\u00e4\u00e4) and a dead member who froze to death before his dreams of success could be realized. They land a gig in Mexico, and the band, including the dead member strapped to the top of their Cadillac, drives there through the country that birthed rock music, meeting various characters along the road to success. Meanwhile, a crazed fan (Kari V\u00e4\u00e4n\u00e4nen) from home chases them down.", "rating": "100", "genre": "Action & Adventure/Art House & International/Comedy/Drama/Musical & Performing Arts", "runtime": "1h 18m", "director": "Aki Kaurism\u00e4ki", "studio": "Megamania,FinnishFilmFoundation,EsselteVideo,VillealfaFilmproductionOy,SvenskaFilminstitutet,Finnkino", "theater_date": "", "dvd_date": "", "box_office": "$9.8K"}, "reviews": {"reviews": ["", "", "", "An immensely funny film", ""], "rating": ["3/5", "4/5", "5/5", "", "3/5"], "fresh": ["fresh", "fresh", "fresh", "fresh", "fresh"], "critic": ["Michael Szymanski", "Emanuel Levy", "Jurgen Fauth", "Frederic and Mary Ann Brussat", "Philip Martin"], "publisher": ["data-qa=\"review-critic-publication\">Zap2it.com", "data-qa=\"review-critic-publication\">EmanuelLevy.Com", "data-qa=\"review-critic-publication\">About.com", "data-qa=\"review-critic-publication\">Spirituality &amp; Practice", "data-qa=\"review-critic-publication\">Arkansas Democrat-Gazette"], "date": ["September 21, 2005", "July 24, 2005", "October 15, 2003", "July 20, 2003", "July 30, 2002"]}}