{"metadata": {"synopsis": "A loner (Benjamin Bratt) and a wealthy businessman (Armand Assante) try to recover treasure from a sunken yacht off the coast of the Bahamas.", "rating": "12", "genre": "Action & Adventure/Drama/Mystery & Suspense/Television", "runtime": "1h 36m", "director": "Guy Ferland", "studio": "Trimark,LionsGateEntertainment", "theater_date": "", "dvd_date": "May 23, 2016", "box_office": ""}, "reviews": {"reviews": ["", "As tedious as watching other people scuba dive."], "rating": ["2/5", "5"], "fresh": ["rotten", "rotten"], "critic": ["Emanuel Levy", "Jaime N. Christley"], "publisher": ["data-qa=\"review-critic-publication\">EmanuelLevy.Com", "data-qa=\"review-critic-publication\">Apollo Guide"], "date": ["August 14, 2005", "May 24, 2001"]}}