{"metadata": {"synopsis": "A time-machine malfunction strands the Doctor (Paul McGann) in 1999 San Francisco and enables archcriminal the Master (Eric Roberts) to escape.", "rating": "48", "genre": "Action & Adventure/Drama/Science Fiction & Fantasy/Television", "runtime": "1h 37m", "director": "Geoffrey Sax", "studio": "", "theater_date": "", "dvd_date": "Feb 8, 2011", "box_office": ""}, "reviews": {"reviews": ["... plays like the missing link between the original run and the 21st Century BBC revision, or maybe an evolutionary offshoot that never thrived."], "rating": [""], "fresh": ["fresh"], "critic": ["Sean Axmaker"], "publisher": ["data-qa=\"review-critic-publication\">MSN.com"], "date": ["February 13, 2011"]}}