{"metadata": {"synopsis": "In 1950s England, sailor Harold Guppy (Rupert Graves) arrives in a small seaside town looking for his estranged brother. After a brief reunion, Harold finds a room for rent in the house of Mrs. Beasley (Julie Walters), her meek husband and their teenage daughter, Joyce (Laura Sadler). It's clear that Harold has a troubled past, but his future is about to get more perilous yet. Despite the rosy surface, Harold soon finds himself in a tawdry sexual tug-of-war that won't end well.", "rating": "14", "genre": "Comedy/Drama", "runtime": "1h 45m", "director": "Philip Goodhew", "studio": "", "theater_date": "", "dvd_date": "", "box_office": "$33.1K"}, "reviews": {"reviews": ["", "", "", "", "", "There was just a growing emptiness that seemed to hang over its denouement...", "Its deadpan humor is entertaining, up to a point, but that point is passed before the movie is quite at its halfway point, and then we're left watching increasingly desperate people who are trapped by one another's madness."], "rating": ["2/5", "2/4", "2.5/4", "3/5", "2.5/4", "C", "2/4"], "fresh": ["rotten", "rotten", "rotten", "fresh", "rotten", "rotten", "rotten"], "critic": ["Emanuel Levy", "", "James Berardinelli", "Marc Savlov", "Steve Rhodes", "Dennis Schwartz", "Roger Ebert"], "publisher": ["data-qa=\"review-critic-publication\">EmanuelLevy.Com", "data-qa=\"review-critic-publication\">Globe and Mail", "data-qa=\"review-critic-publication\">ReelViews", "data-qa=\"review-critic-publication\">Austin Chronicle", "data-qa=\"review-critic-publication\">Internet Reviews", "data-qa=\"review-critic-publication\">Dennis Schwartz Movie Reviews", "data-qa=\"review-critic-publication\">Chicago Sun-Times"], "date": ["July 4, 2005", "April 12, 2002", "January 1, 2000", "January 1, 2000", "January 1, 2000", "January 1, 2000", "January 1, 2000"]}}