{"metadata": {"synopsis": "At the funeral of murdered Johnny Tempio (Vincent Gallo), his brothers, Chez (Chris Penn) and Ray (Christopher Walken), begin plotting their revenge. Believing rival gangster Gaspare (Benicio Del Toro) is responsible for Johnny's death, Chez and Ray set out to find and punish the thugs who killed him, despite the pleadings of their wives (Isabella Rossellini, Annabella Sciorra). As the two get to the bottom of the mystery, Ray must deal with an increasingly unstable Chez.", "rating": "79", "genre": "Action & Adventure/Drama/Mystery & Suspense", "runtime": "1h 38m", "director": "Abel Ferrara", "studio": "OctoberFilms,MDPWorldwide", "theater_date": "", "dvd_date": "Aug 7, 2007", "box_office": "$1.2M"}, "reviews": {"reviews": ["The Funeral is yet another fresh take on the gangster flick.", "Anticlimactic and unconvincing.", "", "Though directed in different style, thematically, this period movie is a companion piece to King of New York and The Bad Lieutenant, forming an urban crime trilogy and representing Ferrara's best work.", "A psychologically strung-out tale stuffed full of ideas and inspired moments.", "A brilliant, very visceral piece of film-making with an infectious strain of morbid humour.", "The corpse, the corpse, the corpse!", "", "One of Ferrara's more bearable fims. Solid performances.", "[Ferrara] still finds sharp new ways to explore the nuances of a trite-sounding story.", "", "", "With a cast like that, one would expect fireworks on the screen. Unfortunately, this never happens.", "", "A strong portrait of gangsters from Abel Ferrara, one of cinemas best provocateurs.", "", "", "", "Some viewers may enjoy watching the lifestyles of the grim and depraved; others will find that sitting through \"The Funeral\" is like going to celluloid hell.", "You're engaged on a moral level rarely found in movies about violence."], "rating": ["3.5/4", "2/5", "3/5", "3/4", "B", "", "4/5", "3/5", "4/5", "3.5/5", "4/5", "6/10", "2/4", "5/5", "3/5", "3/4", "2/5", "4/5", "", ""], "fresh": ["fresh", "rotten", "fresh", "fresh", "fresh", "fresh", "fresh", "fresh", "fresh", "fresh", "fresh", "fresh", "rotten", "fresh", "fresh", "fresh", "rotten", "fresh", "rotten", "fresh"], "critic": ["Jeffrey M. Anderson", "Rob Gonsalves", "Josh Ralske", "Emanuel Levy", "Nick Schager", "", "Cole Smithey", "Emanuel Levy", "Brandon Judell", "Janet Maslin", "Linda Cook", "Dragan Antulov", "David Nusair", "Walter Chaw", "Blake Davis", "Susan Tavernetti", "Jeffrey Westhoff", "Rob Vaux", "Lea Russo", "Desson Thomson"], "publisher": ["data-qa=\"review-critic-publication\">Combustible Celluloid", "data-qa=\"review-critic-publication\">eFilmCritic.com", "data-qa=\"review-critic-publication\">All Movie Guide", "data-qa=\"review-critic-publication\">Variety", "data-qa=\"review-critic-publication\">Lessons of Darkness", "data-qa=\"review-critic-publication\">Time Out", "data-qa=\"review-critic-publication\">ColeSmithey.com", "data-qa=\"review-critic-publication\">EmanuelLevy.Com", "data-qa=\"review-critic-publication\">PopcornQ", "data-qa=\"review-critic-publication\">New York Times", "data-qa=\"review-critic-publication\">Quad City Times (Davenport, IA)", "data-qa=\"review-critic-publication\">rec.arts.movies.reviews", "data-qa=\"review-critic-publication\">Reel Film Reviews", "data-qa=\"review-critic-publication\">Film Freak Central", "data-qa=\"review-critic-publication\">KFOR Channel 4 News", "data-qa=\"review-critic-publication\">Palo Alto Weekly", "data-qa=\"review-critic-publication\">Northwest Herald (Crystal Lake, IL)", "data-qa=\"review-critic-publication\">Flipside Movie Emporium", "data-qa=\"review-critic-publication\">Boxoffice Magazine", "data-qa=\"review-critic-publication\">Washington Post"], "date": ["June 20, 2008", "April 9, 2007", "August 5, 2006", "July 4, 2006", "May 29, 2006", "January 26, 2006", "November 14, 2005", "July 5, 2005", "April 1, 2005", "August 30, 2004", "August 4, 2004", "January 14, 2004", "August 1, 2003", "June 12, 2003", "June 10, 2003", "May 20, 2003", "November 14, 2002", "August 30, 2002", "June 5, 2002", "January 22, 2002"]}}