{"metadata": {"synopsis": "A torrential rainstorm leaves two cousins (Joey Lawrence, Andrew Lawrence) and their captain (Matt Lawrence) stranded on a desert island.", "rating": "63", "genre": "Action & Adventure/Comedy/Drama/Kids & Family/Television", "runtime": "1h 30m", "director": "Michael Lange", "studio": "Miramax", "theater_date": "", "dvd_date": "Aug 21, 2016", "box_office": ""}, "reviews": {"reviews": ["Adventure comedy sequel has mild peril and violence.", "It's a gimmick that works as passable family entertainment for now, but it won't have much of a shelf life."], "rating": ["2/5", ""], "fresh": ["rotten", "fresh"], "critic": ["Alistair Lawrence", "Laura Fries"], "publisher": ["data-qa=\"review-critic-publication\">Common Sense Media", "data-qa=\"review-critic-publication\">Variety"], "date": ["June 16, 2020", "February 23, 2012"]}}