{"metadata": {"synopsis": "A World War I veteran (Gordon MacRae) makes his Indiana sweetheart (Doris Day) wait for marriage while he makes money.", "rating": "80", "genre": "Classics/Comedy/Drama/Kids & Family/Musical & Performing Arts/Romance", "runtime": "1h 42m", "director": "David Butler", "studio": "Paramount,WarnerBrothers/SevenArts", "theater_date": "", "dvd_date": "Dec 3, 2013", "box_office": ""}, "reviews": {"reviews": ["Grand Warner Brothers 1950s Doris Day musical, rich with period music."], "rating": ["4/5"], "fresh": ["fresh"], "critic": ["Steve Crum"], "publisher": ["data-qa=\"review-critic-publication\">Dispatch-Tribune Newspapers"], "date": ["November 17, 2006"]}}