{"metadata": {"synopsis": "Philippe Delambre (Brett Halsey) has been wrestling with his family legacy for years, knowing that his father perished as a result of his experiments in teleportation. Though warned by his uncle Francois (Vincent Price), Philippe insists on refurbishing his father's laboratory and continuing his investigations. The idea would be bad enough on its own, but Philippe hires an assistant who calls himself Alan Hinds (David Frankham) but is actually a wanted criminal.", "rating": "36", "genre": "Classics/Drama/Horror/Science Fiction & Fantasy", "runtime": "1h 20m", "director": "Edward Bernds", "studio": "AssociatedProducers", "theater_date": "", "dvd_date": "Nov 25, 2015", "box_office": ""}, "reviews": {"reviews": ["The first two-thirds are superior to the final stretch.", "Disappointing sequel to the classic horror film, \"The Fly.\"", "Makes for passable 'killing time' entertainment.", "Continuao pouco imaginativa que reutiliza a base do original sem alcanar os mesmos timos resultados.", "", "", "", "", "", "", "", "", "", "removes most of the romantic melodrama that characterized the first film and replaces it with a plot involving criminal intrigue and revenge-inspired murder"], "rating": ["2.5/4", "C", "B-", "2/5", "1/5", "2/5", "3/5", "2/5", "3/5", "3/5", "2/5", "2/5", "5", "2.5/4"], "fresh": ["rotten", "rotten", "fresh", "rotten", "rotten", "rotten", "fresh", "rotten", "fresh", "fresh", "rotten", "rotten", "rotten", "fresh"], "critic": ["Matt Brunson", "Paul Chambers", "Dennis Schwartz", "Pablo Villa\u00e7a", "Michael Szymanski", "Emanuel Levy", "Nell Minow", "Nicolas Lacroix", "Linda Cook", "Ken Hanke", "Philip Martin", "Scott Weinberg", "Brian Webster", "James Kendrick"], "publisher": ["data-qa=\"review-critic-publication\">Film Frenzy", "data-qa=\"review-critic-publication\">Movie Chambers", "data-qa=\"review-critic-publication\">Dennis Schwartz Movie Reviews", "data-qa=\"review-critic-publication\">Cinema em Cena", "data-qa=\"review-critic-publication\">International Press Academy", "data-qa=\"review-critic-publication\">EmanuelLevy.Com", "data-qa=\"review-critic-publication\">Movie Mom", "data-qa=\"review-critic-publication\">Showbizz.net", "data-qa=\"review-critic-publication\">Quad City Times (Davenport, IA)", "data-qa=\"review-critic-publication\">Mountain Xpress (Asheville, NC)", "data-qa=\"review-critic-publication\">Arkansas Democrat-Gazette", "data-qa=\"review-critic-publication\">eFilmCritic.com", "data-qa=\"review-critic-publication\">Apollo Guide", "data-qa=\"review-critic-publication\">Q Network Film Desk"], "date": ["December 15, 2019", "November 1, 2014", "May 3, 2010", "September 11, 2006", "September 23, 2005", "September 4, 2005", "August 31, 2004", "December 13, 2002", "November 15, 2002", "September 24, 2002", "July 26, 2002", "July 26, 2002", "July 25, 2001", "February 27, 2001"]}}