{"metadata": {"synopsis": "The Jolly Boys, a group of London booze hounds, are stunned to learn that charter member \"Spider\" Dale (Andy Serkis) is marrying his girlfriend, Annie (Rebecca Craig). Hoping to scuttle the engagement by capturing footage of his friend's epic partying, \"Des\" Dixon (Milo Twomey) films Spider's last months of freedom. Taking the form of an amateur video, this comedy follows the Jolly Boys, who soon realize that yet another member (Sacha Baron Cohen) is set to be married.", "rating": "29", "genre": "Comedy", "runtime": "1h 27m", "director": "Christopher Payne", "studio": "", "theater_date": "", "dvd_date": "Apr 12, 2017", "box_office": ""}, "reviews": {"reviews": [""], "rating": ["3/5"], "fresh": ["fresh"], "critic": ["Christopher Null"], "publisher": ["data-qa=\"review-critic-publication\">Filmcritic.com"], "date": ["January 1, 1800"]}}