{"metadata": {"synopsis": "Flash (Larry \"Buster\" Crabbe) saves Earth from purple death sent by planet Mongo's Ming the Merciless (Charles Middleton).", "rating": "88", "genre": "Action & Adventure/Classics/Science Fiction & Fantasy", "runtime": "1h 40m", "director": "Ford Beebe, Ray Taylor", "studio": "UniversalPictures", "theater_date": "Mar 3, 1940", "dvd_date": "Mar 4, 2020", "box_office": ""}, "reviews": {"reviews": ["The serial's production values compensate for the usual Universal cheapness of stock footage and newsreel sequences.", "", "Third and final (and actually made in 1940) Flash Gordon serial. Still fun.", "", "Though played out against some lavish backdrops, 'Universe' is easily the weakest of the Flash serials.", "", "The prettiest of the Flash Gordon serials, even though like most Universal chapterplays, it is filled with stock footage and choppy editing.", "Of course, it's corny and juvenile but that's the point."], "rating": ["3/4", "3/5", "4/5", "3/5", "", "3/5", "3/5", "6/10"], "fresh": ["fresh", "fresh", "fresh", "fresh", "fresh", "fresh", "fresh", "rotten"], "critic": ["Bob Bloom", "Emanuel Levy", "Ken Hanke", "Carol Cling", "James Sanford", "Philip Martin", "Bob Bloom", "John J. Puccio"], "publisher": ["data-qa=\"review-critic-publication\">Journal and Courier (Lafayette, IN)", "data-qa=\"review-critic-publication\">EmanuelLevy.Com", "data-qa=\"review-critic-publication\">Mountain Xpress (Asheville, NC)", "data-qa=\"review-critic-publication\">Las Vegas Review-Journal", "data-qa=\"review-critic-publication\">Kalamazoo Gazette", "data-qa=\"review-critic-publication\">Arkansas Democrat-Gazette", "data-qa=\"review-critic-publication\">rec.arts.movies.reviews", "data-qa=\"review-critic-publication\">Movie Metropolis"], "date": ["July 18, 2016", "August 26, 2005", "August 24, 2003", "August 22, 2003", "July 2, 2003", "November 25, 2002", "September 8, 2002", "January 1, 2000"]}}