{"metadata": {"synopsis": "An Ohio heart surgeon (D.B. Sweeney) shares a roof with the meddling grandfather (Peter Falk) who raised him.", "rating": "29", "genre": "Comedy", "runtime": "1h 48m", "director": "Peter Yates", "studio": "", "theater_date": "", "dvd_date": "Mar 22, 2016", "box_office": "$12.1M"}, "reviews": {"reviews": ["", "", "", "A pretty forgotten little movie that has some poignant moments.", "", "Falk is good, but this is ultimately an exercise in shameless manipulation.", "", "Wonderful film that salutes the vitsal connections between grandparents and grandchildren.", "", "", "", "", "", "The pieces were in place for a nice little story, but by trying to do too much with it, Roommates overshoots the runway."], "rating": ["C-", "2/5", "3/5", "3/5", "2/5", "1/5", "2.5/4", "", "2/5", "4/10", "1/4", "2.5/4", "3.5/5", "2.5/4"], "fresh": ["rotten", "rotten", "fresh", "fresh", "rotten", "rotten", "rotten", "fresh", "rotten", "rotten", "rotten", "rotten", "fresh", "rotten"], "critic": ["Lisa Schwarzbaum", "Emanuel Levy", "Robin Clifford", "Steve Crum", "Frank Swietek", "Rob Thomas", "Susan Tavernetti", "Frederic and Mary Ann Brussat", "Scott Weinberg", "Scott Renshaw", "Madeleine Williams", "James Berardinelli", "Robert Faires", "Roger Ebert"], "publisher": ["data-qa=\"review-critic-publication\">Entertainment Weekly", "data-qa=\"review-critic-publication\">EmanuelLevy.Com", "data-qa=\"review-critic-publication\">Reeling Reviews", "data-qa=\"review-critic-publication\">Kansas City Kansan", "data-qa=\"review-critic-publication\">One Guy&#39;s Opinion", "data-qa=\"review-critic-publication\">Capital Times (Madison, WI)", "data-qa=\"review-critic-publication\">Palo Alto Weekly", "data-qa=\"review-critic-publication\">Spirituality &amp; Practice", "data-qa=\"review-critic-publication\">eFilmCritic.com", "data-qa=\"review-critic-publication\">rec.arts.movies.reviews", "data-qa=\"review-critic-publication\">Cinematter", "data-qa=\"review-critic-publication\">ReelViews", "data-qa=\"review-critic-publication\">Austin Chronicle", "data-qa=\"review-critic-publication\">Chicago Sun-Times"], "date": ["September 7, 2011", "July 16, 2005", "November 19, 2004", "October 15, 2004", "May 6, 2004", "October 9, 2003", "May 20, 2003", "August 30, 2002", "July 26, 2002", "January 1, 2000", "January 1, 2000", "January 1, 2000", "January 1, 2000", "January 1, 2000"]}}