{"metadata": {"synopsis": "Teenage Gidget (Cindy Carol) and boyfriend Moondoggie (James Darren) cause romantic confusion on vacation in Italy.", "rating": "53", "genre": "Comedy/Romance", "runtime": "1h 43m", "director": "Paul Wendkos", "studio": "ColumbiaPicturesCorporation", "theater_date": "", "dvd_date": "Dec 3, 2018", "box_office": ""}, "reviews": {"reviews": ["Nightmarish and absurd in equal portion."], "rating": ["2/4"], "fresh": ["rotten"], "critic": ["Walter Chaw"], "publisher": ["data-qa=\"review-critic-publication\">Film Freak Central"], "date": ["November 18, 2004"]}}