{"metadata": {"synopsis": "Five stories center around a werewolf, a feudal landlord, peasants, a ghost, and a mother (Margarita Lozano) and her sons.", "rating": "92", "genre": "Art House & International/Comedy/Drama", "runtime": "3h 8m", "director": "Paolo Taviani, Vittorio Taviani", "studio": "Paramount", "theater_date": "", "dvd_date": "Mar 8, 2017", "box_office": "$205.0K"}, "reviews": {"reviews": ["Recognized for the splendid landscape photography by Giuseppe Land.", ""], "rating": ["B-", "4/5"], "fresh": ["fresh", "fresh"], "critic": ["Dennis Schwartz", "Emanuel Levy"], "publisher": ["data-qa=\"review-critic-publication\">Dennis Schwartz Movie Reviews", "data-qa=\"review-critic-publication\">EmanuelLevy.Com"], "date": ["March 11, 2016", "July 21, 2005"]}}