{"metadata": {"synopsis": "A hi-tech toy factory falls into the hands of an army general who turns the models into killing machines. The deceased owner's children know what's afoot and, although apparently powerless, have to find a way of bringing down the nightmarish empire that is being constructed under their noses.", "rating": "30", "genre": "Action & Adventure/Comedy", "runtime": "2h 1m", "director": "Barry Levinson", "studio": "BaltimorePictures,TwentiethCenturyFox", "theater_date": "", "dvd_date": "Nov 30, 2016", "box_office": "$21.3M"}, "reviews": {"reviews": ["No child I know would benefit from seeing this work, and certainly no adult.", "The failure of Barry Levinson's Toys is of a different order: it's the kind of folly only a very fine filmmaker could make, a labor of misguided love.", "Robin Williams and Barry Levinson romp hand-in-hand through the wonderful, wacky world of whimsical surrealism", "Whether it's a glorious, intoxicating failure or a dire, unwatchable failure is right down to personal taste.", "", "Despite title, edgy fantasy-fable isn't geared toward kids.", "", "", "", "", "", "A big, colorful movie. The film is absurd, but likeable.", "", "Unwatchable muck.", "", "It's a terminally flawed film, and almost gleefully so.", "Batteries 'definitely' were'nt included", "", "Beware of any film where the most interesting character is a machine.", ""], "rating": ["", "", "", "3/5", "F", "3/5", "3/5", "C", "2/5", "1/5", "3/5", "3/5", "2/5", "0/5", "3/5", "2/5", "2/5", "1/5", "1/5", "2/5"], "fresh": ["rotten", "rotten", "fresh", "fresh", "rotten", "fresh", "fresh", "rotten", "rotten", "rotten", "fresh", "fresh", "rotten", "rotten", "fresh", "rotten", "rotten", "rotten", "rotten", "rotten"], "critic": ["Vanessa Letts", "David Ansen", "Malcolm Johnson", "Tim Brayton", "Owen Gleiberman", "Charles Cassady", "Michael Szymanski", "Emanuel Levy", "Jules Brenner", "Jake Euker", "Mike McGranaghan", "Alex Sandell", "Philip Martin", "Ken Hanke", "Joshua Tyler", "Widgett Walls", "Caffeinated Clint", "Jeffrey Westhoff", "Rob Vaux", "Scott Weinberg"], "publisher": ["data-qa=\"review-critic-publication\">The Spectator", "data-qa=\"review-critic-publication\">Newsweek", "data-qa=\"review-critic-publication\">Hartford Courant", "data-qa=\"review-critic-publication\">Alternate Ending", "data-qa=\"review-critic-publication\">Entertainment Weekly", "data-qa=\"review-critic-publication\">Common Sense Media", "data-qa=\"review-critic-publication\">Wordmag.com", "data-qa=\"review-critic-publication\">EmanuelLevy.Com", "data-qa=\"review-critic-publication\">Cinema Signals", "data-qa=\"review-critic-publication\">F5 (Wichita, KS)", "data-qa=\"review-critic-publication\">Aisle Seat", "data-qa=\"review-critic-publication\">Juicy Cerebellum", "data-qa=\"review-critic-publication\">Arkansas Democrat-Gazette", "data-qa=\"review-critic-publication\">Mountain Xpress (Asheville, NC)", "data-qa=\"review-critic-publication\">CinemaBlend", "data-qa=\"review-critic-publication\">Needcoffee.com", "data-qa=\"review-critic-publication\">Moviehole", "data-qa=\"review-critic-publication\">Northwest Herald (Crystal Lake, IL)", "data-qa=\"review-critic-publication\">Flipside Movie Emporium", "data-qa=\"review-critic-publication\">eFilmCritic.com"], "date": ["July 25, 2018", "May 31, 2018", "May 31, 2018", "September 7, 2017", "September 7, 2011", "August 31, 2010", "September 23, 2005", "June 19, 2005", "February 13, 2005", "June 4, 2004", "September 4, 2003", "June 25, 2003", "May 23, 2003", "May 12, 2003", "December 25, 2002", "November 8, 2002", "September 17, 2002", "August 16, 2002", "August 13, 2002", "July 26, 2002"]}}