{"metadata": {"synopsis": "", "rating": "82", "genre": "Art House & International/Drama", "runtime": "", "director": "Rithy Panh", "studio": "", "theater_date": "", "dvd_date": "", "box_office": ""}, "reviews": {"reviews": ["It's occasionally fascinating, all the same, as a window on a very different world.", "There's a cobra, a flood, a death, financial misery and more angst than rice. If anything, this is not a promotional film for the joys of a career in Cambodian agriculture."], "rating": ["", "2/5"], "fresh": ["fresh", "rotten"], "critic": ["Sheila Johnston", "Phil Hall"], "publisher": ["data-qa=\"review-critic-publication\">Independent (UK)", "data-qa=\"review-critic-publication\">Film Threat"], "date": ["March 29, 2019", "October 5, 2006"]}}