{"metadata": {"synopsis": "A medieval muscleman (Richard Hill) sword-fights a sun lover on his way to free a princess (Barbi Benton) from a wizard's castle.", "rating": "26", "genre": "Action & Adventure/Science Fiction & Fantasy", "runtime": "1h 20m", "director": "James Sbardellati", "studio": "AriesCinematogr\u00e1ficaArgentina,PaloAltoProductions", "theater_date": "", "dvd_date": "Jun 18, 2018", "box_office": ""}, "reviews": {"reviews": ["Bare breasts and brutal violence always seem to present themselves just when audiences might start to focus on the more nonsensical bits."], "rating": ["6/10"], "fresh": ["fresh"], "critic": ["Mike Massie"], "publisher": ["data-qa=\"review-critic-publication\">Gone With The Twins"], "date": ["August 31, 2020"]}}