{"metadata": {"synopsis": "Biracial detectives (Alex Rocco, Hari Rhodes) track loot from a fundraiser for the first black governor of Michigan.", "rating": "25", "genre": "Action & Adventure/Cult Movies/Drama/Mystery & Suspense", "runtime": "1h 50m", "director": "Arthur Marks", "studio": "", "theater_date": "", "dvd_date": "May 23, 2016", "box_office": "$2.1K"}, "reviews": {"reviews": ["Its sleaze does justice to the downtrodden once mighty city.", "A gritty, disturbing evocation of the ambiguities of big-city police work.", "", "Detroit 9000 is a tough, cynical, big-city cop movie that occasionally tries to rise above its genre but doesn't quite make it.", "", "", "As an example of the genre the French call a policier, the film is unexceptional.", ""], "rating": ["C+", "", "2/5", "2/4", "2.5/5", "6", "2/5", "8/10"], "fresh": ["rotten", "fresh", "rotten", "rotten", "rotten", "rotten", "rotten", "fresh"], "critic": ["Dennis Schwartz", "Don Druker", "Emanuel Levy", "Roger Ebert", "Marc Savlov", "Dan Jardine", "Lawrence Van Gelder", "Harvey S. Karten"], "publisher": ["data-qa=\"review-critic-publication\">Dennis Schwartz Movie Reviews", "data-qa=\"review-critic-publication\">Chicago Reader", "data-qa=\"review-critic-publication\">EmanuelLevy.Com", "data-qa=\"review-critic-publication\">Chicago Sun-Times", "data-qa=\"review-critic-publication\">Austin Chronicle", "data-qa=\"review-critic-publication\">Apollo Guide", "data-qa=\"review-critic-publication\">New York Times", "data-qa=\"review-critic-publication\">Compuserve"], "date": ["February 21, 2015", "April 4, 2013", "August 13, 2005", "October 23, 2004", "September 9, 2002", "January 1, 2000", "January 1, 2000", "January 1, 2000"]}}