{"metadata": {"synopsis": "An ex-convict (F. Murray Abraham) returns to fencing at the academy of a ruthless champion (Eric Roberts) whose father he killed.", "rating": "76", "genre": "Action & Adventure/Drama", "runtime": "1h 31m", "director": "Jeremy Kagan", "studio": "", "theater_date": "", "dvd_date": "", "box_office": ""}, "reviews": {"reviews": ["", "By the Sword is about fencing, a sport not often covered in the movies, and it handles it in an interesting way - although the surrounding plot is a little too neat and obvious to really carry the material."], "rating": ["2/5", "2.5/4"], "fresh": ["rotten", "rotten"], "critic": ["Emanuel Levy", "Roger Ebert"], "publisher": ["data-qa=\"review-critic-publication\">EmanuelLevy.Com", "data-qa=\"review-critic-publication\">Chicago Sun-Times"], "date": ["August 10, 2005", "January 1, 2000"]}}