{"metadata": {"synopsis": "When a group of Italian soldiers washes up on a Greek island after the Allies sink their ship, the men initially believe that the region is deserted. However, they discover that the islanders have been in hiding, and the soldiers, winning the trust of the locals, gradually become part of the community. As the Italians, including Lt. Raffaele Montini (Claudio Bigagli), ease into an idyllic existence, they begin to forget about war and pursue romance with the lovely women of the island.", "rating": "79", "genre": "Art House & International/Comedy/Drama/Romance", "runtime": "1h 45m", "director": "Gabriele Salvatores", "studio": "Miramax,SilvioBerlusconiCommunications", "theater_date": "", "dvd_date": "", "box_office": ""}, "reviews": {"reviews": ["Salvatores has fashioned a likable, crowd-pleasing story, complete with a touching aftermath. But when one compares it with the foreign films eligible for the 1991 Oscars, Mediteranneo seems obvious and shallow.", "", "", "", "", "", "", "", "Shows how easily men give up the rigors of war for the delights of relaxation and camaraderie.", "", "", "", "", ""], "rating": ["", "4/5", "3/5", "3/5", "4/5", "3/5", "1/5", "1/5", "", "4/5", "4/5", "", "3.5/5", "2.5/4"], "fresh": ["fresh", "fresh", "fresh", "fresh", "fresh", "fresh", "rotten", "rotten", "fresh", "fresh", "fresh", "fresh", "fresh", "rotten"], "critic": ["Malcolm Johnson", "Cole Smithey", "Philip Martin", "Emanuel Levy", "Daniel M. Kimmel", "Carol Cling", "Jeffrey Westhoff", "John Esther", "Frederic and Mary Ann Brussat", "Brandon Judell", "Oz", "Mark R. Leeper", "Kathleen Maher", "James Berardinelli"], "publisher": ["data-qa=\"review-critic-publication\">Hartford Courant", "data-qa=\"review-critic-publication\">ColeSmithey.com", "data-qa=\"review-critic-publication\">Arkansas Democrat-Gazette", "data-qa=\"review-critic-publication\">EmanuelLevy.Com", "data-qa=\"review-critic-publication\">Worcester Telegram &amp; Gazette", "data-qa=\"review-critic-publication\">Las Vegas Review-Journal", "data-qa=\"review-critic-publication\">Northwest Herald (Crystal Lake, IL)", "data-qa=\"review-critic-publication\">Pasadena Weekly", "data-qa=\"review-critic-publication\">Spirituality &amp; Practice", "data-qa=\"review-critic-publication\">PopcornQ", "data-qa=\"review-critic-publication\">eFilmCritic.com", "data-qa=\"review-critic-publication\">rec.arts.movies.reviews", "data-qa=\"review-critic-publication\">Austin Chronicle", "data-qa=\"review-critic-publication\">ReelViews"], "date": ["March 4, 2019", "November 1, 2005", "July 15, 2005", "July 7, 2005", "April 27, 2005", "January 23, 2004", "August 29, 2003", "August 21, 2003", "July 19, 2003", "December 19, 2002", "November 4, 2002", "January 1, 2000", "January 1, 2000", "January 1, 2000"]}}