{"metadata": {"synopsis": "\"Goya in Bordeaux,\" written and directed by Carlos Saura, explores the experiences and artistic evolution of the man considered to be the most important artist of the modern era, Francisco Goya. The final months of his life form the background to a story which is rooted in his evolution as a man, his work and in his private obsessions.", "rating": "54", "genre": "Art House & International/Drama", "runtime": "1h 42m", "director": "Carlos Saura", "studio": "Televisi\u00f3nEspa\u00f1ola(TVE),ViaDigital,RadiotelevisioneItaliana(RAI)[it],LolafilmsS.A.,ItalianInternationalFilm", "theater_date": "Sep 15, 2000", "dvd_date": "Mar 5, 2013", "box_office": "$716.6K"}, "reviews": {"reviews": ["pedestrian introduction to his works and supplying some tepid amusement for his connoisseurs", "", "", "", "Magnificent biopic of painter, gripping and inventive", "", "", "", "", "Offers an unflinching and original look at the Spanish painter who spent his last years living in exile in France.", "", "", "When the film, as it frequently does, sticks to traditional dialog sans music, it quickly grinds to a halt.", "", "A plodding production.", "", "Despite good intentions, Goya in Bordeaux ends up more frustrating than entertaining.", "A visually pleasing but unmoving biopic of the 18th-century Spanish painter Francisco Goya.", "Lushly photographed and grandly conceived, Carlos Saura's Goya in Bordeaux never comes alive.", "Lushly photographed and grandly conceived, Carlos Saura's Goya in Bordeaux never comes alive."], "rating": ["C", "3/5", "4/5", "3/5", "5/5", "2.5/4", "0/4", "B", "2.5/4", "", "4", "3/5", "7/10", "8/10", "2/4", "2/5", "", "C", "2/4", ""], "fresh": ["rotten", "fresh", "fresh", "fresh", "fresh", "rotten", "rotten", "fresh", "rotten", "fresh", "rotten", "fresh", "fresh", "fresh", "rotten", "rotten", "rotten", "rotten", "rotten", "rotten"], "critic": ["John A. Nesbit", "Jim Lane", "", "Emanuel Levy", "Michael E. Grost", "Susan Tavernetti", "Ted Murphy", "William Arnold", "", "Frederic and Mary Ann Brussat", "Ryan Cracknell", "Christopher Null", "Steve Rhodes", "Harvey S. Karten", "Peter Stack", "Marjorie Baumgarten", "Daniel Eagan", "Dennis Schwartz", "Roger Ebert", ""], "publisher": ["data-qa=\"review-critic-publication\">Old School Reviews", "data-qa=\"review-critic-publication\">Sacramento News &amp; Review", "data-qa=\"review-critic-publication\">Empire Magazine", "data-qa=\"review-critic-publication\">EmanuelLevy.Com", "data-qa=\"review-critic-publication\">Classic Film and Television", "data-qa=\"review-critic-publication\">Palo Alto Weekly", "data-qa=\"review-critic-publication\">Hollywood.com", "data-qa=\"review-critic-publication\">Seattle Post-Intelligencer", "data-qa=\"review-critic-publication\">Globe and Mail", "data-qa=\"review-critic-publication\">Spirituality &amp; Practice", "data-qa=\"review-critic-publication\">Apollo Guide", "data-qa=\"review-critic-publication\">Filmcritic.com", "data-qa=\"review-critic-publication\">Internet Reviews", "data-qa=\"review-critic-publication\">Compuserve", "data-qa=\"review-critic-publication\">San Francisco Chronicle", "data-qa=\"review-critic-publication\">Austin Chronicle", "data-qa=\"review-critic-publication\">Film Journal International", "data-qa=\"review-critic-publication\">Dennis Schwartz Movie Reviews", "data-qa=\"review-critic-publication\">Chicago Sun-Times", "data-qa=\"review-critic-publication\">E! Online"], "date": ["January 22, 2011", "August 7, 2008", "December 30, 2006", "July 13, 2005", "January 24, 2005", "May 20, 2003", "May 2, 2003", "April 3, 2002", "March 19, 2002", "March 16, 2002", "February 7, 2001", "February 1, 2001", "January 30, 2001", "January 30, 2001", "January 1, 2000", "January 1, 2000", "January 1, 2000", "January 1, 2000", "January 1, 2000", "January 1, 2000"]}}